{
  "Name": "Mine Shaft",
  "Description": "It's a hole.",
  "Price": 0,
  "Category": "Crafting",
  "Recipe":
  {
    "ResultCount": 1,
    "Ingredients": [
        {
        "Object": 390,
        "Count": 200,
        },
    ],
    "CanPurchase": false,
    "SkillUnlockName": "Mining",
    "SkillUnlockLevel": 6
  },
  "NameLocalization":
  {
    // "es": "",
    // "ko": "",
    // "de": "",
    // "fr": "",
    // "hu": "",
    // "it": "",
    // "ja": "",
    // "pt": "",
    // "ru": "",
    // "tr": "",
    // "zh":"",
  },
  "DescriptionLocalization":
  {
    // "es": "",
    // "ko": "",
    // "de": "",
    // "fr": "",
    // "hu": "",
    // "it": "",
    // "ja": "",
    // "pt": "",
    // "ru": "",
    // "tr": "",
    // "zh":"",
  },
}
